{
  "LevelOfDetail": {
    "label": "Level of Detail",
    "description": "The amount of specificity and granularity provided about the cooking process, including ingredient measurements and step-by-step instructions.",
    "values": [
      "High",
      "Medium",
      "Low"
    ],
    "examples": {
      "High": [
        "step1_2 (detailed bread preparation)",
        "step3_3 (specific ingredient quantities)"
      ],
      "Medium": [
        "step1_9 (general mushroom preparation)",
        "step3_11 (sausage cooking with some detail)"
      ],
      "Low": [
        "step1_5 (vague on quantities)",
        "step1_6 (minimal process details)"
      ]
    }
  },
  "ExplanationDepth": {
    "label": "Explanation Depth",
    "description": "The extent to which the reasoning behind actions or choices is explained, providing viewers with context and understanding of the cooking process.",
    "values": [
      "In-depth",
      "Moderate",
      "Surface-level"
    ],
    "examples": {
      "In-depth": [
        "step1_4 (explanation of mushroom preparation)",
        "step3_9 (detailed reasoning behind cooking techniques)"
      ],
      "Moderate": [
        "step2_0 (brief mention of seasoning)",
        "step3_2 (quick explanation of ingredient addition)"
      ],
      "Surface-level": [
        "step1_5 (no explanation of steps)",
        "step2_5 (lacks reasoning behind actions)"
      ]
    }
  },
  "Personalization": {
    "label": "Personalization",
    "description": "The degree to which the narrator includes personal anecdotes, preferences, or suggestions, creating a more intimate and engaging viewer experience.",
    "values": [
      "High",
      "Medium",
      "Low"
    ],
    "examples": {
      "High": [
        "step1_7 (personal preference for sausage type)",
        "step3_4 (specific brand and ingredients used)"
      ],
      "Medium": [
        "step1_9 (general tips for mushroom preparation)",
        "step3_11 (mentions of personal cooking choices)"
      ],
      "Low": [
        "step1_3 (strictly instructional with no personal input)",
        "step2_0 (focused solely on the recipe)"
      ]
    }
  },
  "InstructionalApproach": {
    "label": "Instructional Approach",
    "description": "The method by which cooking instructions are presented, ranging from direct, step-by-step guidance to more conceptual, flexible suggestions.",
    "values": [
      "Direct",
      "Guidance",
      "Conceptual"
    ],
    "examples": {
      "Direct": [
        "step4_1 (explicit stuffing instructions)",
        "step5_0 (specific baking directions)"
      ],
      "Guidance": [
        "step3_7 (general instructions with some flexibility)",
        "step4_7 (broad advice on filling mushrooms)"
      ],
      "Conceptual": [
        "step1_9 (conceptual guidance on mushroom prep)",
        "step3_11 (encourages adaptation of recipe)"
      ]
    }
  }
}