[
    {
        "id": "75p4UHRIMcU",
        "x": -1.0250158309936523,
        "y": -0.4485056400299072,
        "color": "rgba(103, 84, 15, 1)",
        "data": {
            "longtext": [
                "I like to use a carving fork to twirl the pasta into a giant cylinder, like this one, for presentation on a long, narrow plate.",
                "We are then, of course, going to want to top this hedonistic helix with the remaining guanciale from the bottom of the pan, along with any remnants of that creamy sauce.",
                "And there you have it, folks. I'm gonna say it one last time. Carbonara. In its purest, most authentic and traditional form."
            ]
        }
    },
    {
        "id": "dzyXBU3dIys",
        "x": 1.1814937591552734,
        "y": 0.14347831904888153,
        "color": "rgba(101, 167, 97, 1)",
        "data": {
            "longtext": [
                "I like to use a carving fork to twirl the pasta into a giant cylinder, like this one, for presentation on a long, narrow plate.",
                "We are then, of course, going to want to top this hedonistic helix with the remaining guanciale from the bottom of the pan, along with any remnants of that creamy sauce."
            ]
        }
    },
    {
        "id": "D_2DBLAt57c",
        "x": -0.6604715585708618,
        "y": -1.3001575469970703,
        "color": "rgba(79, 111, 156, 1)",
        "data": {
            "longtext": [
                "I like to use a carving fork to twirl the pasta into a giant cylinder, like this one, for presentation on a long, narrow plate.",
                "We are then, of course, going to want to top this hedonistic helix with the remaining guanciale from the bottom of the pan, along with any remnants of that creamy sauce."
            ]
        }
    },
    {
        "id": "3AAdKl1UYZs",
        "x": 1.2495406866073608,
        "y": -0.14596903324127197,
        "color": "rgba(103, 94, 230, 1)",
        "data": {
            "longtext": [
                "I like to use a carving fork to twirl the pasta into a giant cylinder, like this one, for presentation on a long, narrow plate.",
                "We are then, of course, going to want to top this hedonistic helix with the remaining guanciale from the bottom of the pan, along with any remnants of that creamy sauce."
            ]
        }
    },
    {
        "id": "NqFi90p38N8",
        "x": -0.7455469369888306,
        "y": 1.7511537075042725,
        "color": "rgba(152, 167, 108, 1)",
        "data": {
            "longtext": [
                "I like to use a carving fork to twirl the pasta into a giant cylinder, like this one, for presentation on a long, narrow plate.",
                "We are then, of course, going to want to top this hedonistic helix with the remaining guanciale from the bottom of the pan, along with any remnants of that creamy sauce.",
                "Ensure the pasta is twirled into a neat cylinder for an appealing presentation."
            ]
        }
    }
]